image_processing_teste/__init__.py
image_processing_teste/processing/__init__.py
image_processing_teste/processing/combination.py
image_processing_teste/processing/transformation.py
image_processing_teste/utils/__init__.py
image_processing_teste/utils/io.py
image_processing_teste/utils/plot.py
image_processing_teste2-0.0.2.dist-info/METADATA
image_processing_teste2-0.0.2.dist-info/WHEEL
image_processing_teste2-0.0.2.dist-info/top_level.txt
image_processing_teste2-0.0.2.dist-info/RECORD
